<?xml version="1.0" ?><unit><commonInformation author="MA" modifyDate="2019.04.09" remark="No" version="0.0"/><memberType ID="u-08" MetaModelID="p-67.258" memberRole="unit" memberTypeCode="1" resource="166.60617"/><pattern path="..\patterns\pattern1.xml"><target pID="p22"/><now pID="p24"/></pattern><effector endowment="2.85702" remain="0.00617" scale="8">
<advisor aID="a-05" strength="0.38804"/><advisor aID="a-04" strength="0.84804"/><advisor aID="a-06" strength="0.24869"/><advisor aID="a-19" strength="0.13042"/><advisor aID="a-00" strength="1.19615"/><advisor aID="a-18" strength="0.01393"/><advisor aID="a-08" strength="0.01631"/><advisor aID="a-11" strength="0.00927"/></effector><decider depth="3" selfConfidence="7.39802" strategy="normal"><decisionList scale="0">
</decisionList></decider><executor mutationRate="0.0005" scale="6" selfDegeneration="0.38895" selfDiscipline="5.57139">
<monitor mID="m-15"/><monitor mID="m-06"/><monitor mID="m-11"/><monitor mID="m-12"/><monitor mID="m-16"/><monitor mID="m-14"/></executor><parameter endowment="8.71783" remain="0.00262" scale="6">
<cUnit strength="5.91707" uID="u-00"/><cUnit strength="2.06431" uID="u-03"/><cUnit strength="0.35065" uID="u-04"/><cUnit strength="0.02287" uID="u-05"/><cUnit strength="0.32995" uID="u-06"/><cUnit strength="0.03036" uID="u-07"/></parameter><comment>default</comment></unit>