<?xml version="1.0" ?><unit><commonInformation author="MA" modifyDate="2019.04.09" remark="No" version="0.0"/><memberType ID="u-01" MetaModelID="p-67.258" memberRole="unit" memberTypeCode="1" resource="4021.98687"/><pattern path="C:simulation/patterns/ptn-1.xml"><target pID="p22"/><now pID="p24"/></pattern><effector endowment="18.05077" remain="1.74253" scale="1">
<advisor aID="a-14" strength="16.30824"/></effector><decider depth="4" selfConfidence="2.3943" strategy="normal"><decisionList scale="0">
</decisionList></decider><executor mutationRate="0.0005" scale="7" selfDegeneration="0.95327" selfDiscipline="0.2744">
<monitor mID="m-02"/><monitor mID="m-01"/><monitor mID="m-13"/><monitor mID="m-08"/><monitor mID="m-05"/><monitor mID="m-12"/><monitor mID="m-07"/></executor><parameter endowment="6.61409" remain="6.61409" scale="0">
</parameter><comment>default</comment></unit>