<?xml version="1.0" ?><unit><commonInformation author="MA" modifyDate="2019.04.09" remark="No" version="0.0"/><memberType ID="u-07" MetaModelID="p-67.258" memberRole="unit" memberTypeCode="1" resource="109.68263"/><pattern path=".\patterns\pattern1.xml"><target pID="p22"/><now pID="p24"/></pattern><effector endowment="3.64401" remain="0.04673" scale="2">
<advisor aID="a-07" strength="3.4118"/><advisor aID="a-14" strength="0.18548"/></effector><decider depth="2" selfConfidence="7.03965" strategy="normal"><decisionList scale="0">
</decisionList></decider><executor mutationRate="0.0005" scale="0" selfDegeneration="0.17996" selfDiscipline="3.23566">
</executor><parameter endowment="12.12022" remain="0.00024" scale="11">
<cUnit strength="10.06038" uID="u-01"/><cUnit strength="2.00562" uID="u-02"/><cUnit strength="0.03816" uID="u-03"/><cUnit strength="0.00462" uID="u-05"/><cUnit strength="0.00222" uID="u-06"/><cUnit strength="0.00721" uID="u-08"/><cUnit strength="0.0006" uID="u-14"/><cUnit strength="0.00026" uID="u-16"/><cUnit strength="2e-05" uID="u-17"/><cUnit strength="0.00085" uID="u-18"/><cUnit strength="5e-05" uID="u-19"/></parameter><comment>default</comment></unit>