<?xml version="1.0" ?><unit><commonInformation author="MA" modifyDate="2019.04.09" remark="No" version="0.0"/><memberType ID="u-08" MetaModelID="p-67.258" memberRole="unit" memberTypeCode="1" resource="181.70073"/><pattern path=".\patterns\pattern1.xml"><target pID="p22"/><now pID="p24"/></pattern><effector endowment="4.00801" remain="0.01694" scale="8">
<advisor aID="a-11" strength="2.45003"/><advisor aID="a-10" strength="1.23677"/><advisor aID="a-06" strength="0.09873"/><advisor aID="a-01" strength="0.08581"/><advisor aID="a-00" strength="0.01901"/><advisor aID="a-08" strength="0.00589"/><advisor aID="a-09" strength="0.08516"/><advisor aID="a-16" strength="0.00967"/></effector><decider depth="4" selfConfidence="1.61319" strategy="normal"><decisionList scale="0">
</decisionList></decider><executor mutationRate="0.0005" scale="3" selfDegeneration="0.28535" selfDiscipline="0.95889">
<monitor mID="m-06"/><monitor mID="m-18"/><monitor mID="m-15"/></executor><parameter endowment="12.3981" remain="0.00247" scale="9">
<cUnit strength="11.31098" uID="u-01"/><cUnit strength="0.1138" uID="u-02"/><cUnit strength="0.90548" uID="u-06"/><cUnit strength="0.0375" uID="u-07"/><cUnit strength="0.00922" uID="u-11"/><cUnit strength="0.01162" uID="u-14"/><cUnit strength="0.00022" uID="u-15"/><cUnit strength="0.0031" uID="u-17"/><cUnit strength="0.00371" uID="u-19"/></parameter><comment>default</comment></unit>