<?xml version="1.0" ?><monitor><commonInformation author="MA" modifyDate="2019.04.09" remark="No" version="0.0"/><memberType ID="m-01" MetaModelID="p-67.258" endowment="14.32822" memberRole="monitor" memberTypeCode="3"/><pattern path=".\patterns\pattern1.xml"/><monitoring scale="22" value="('p0', 'p3')|('p13', 'p16')|('p4', 'p7')|('p5', 'p9')|('p2', 'p6')|('p6', 'p8')|('p19', 'p23')|('p9', 'p12')|('p18', 'p22')|('p14', 'p18')|('p17', 'p21')|('p16', 'p19')|('p9', 'p11')|('p10', 'p15')|('p19', 'p22')|('p0', 'p4')|('p4', 'p8')|('p20', 'p23')|('p7', 'p11')|('p7', 'p10')|('p24', 'p1')|('p11', 'p15')"/><unitList remaining="0.00216" scale="6">
<unit strength="12.10174" uID="u-00"/><unit strength="1.63714" uID="u-03"/><unit strength="0.49263" uID="u-08"/><unit strength="0.00754" uID="u-14"/><unit strength="0.08521" uID="u-16"/><unit strength="0.0018" uID="u-19"/></unitList></monitor>